{
  "manifestVersion": "3.2",
  "admin": {
    "address": "0xeff7FbF1522031bB34b372002EF282B8DBB95B8E",
    "txHash": "0x472b6449ad9791c27a404b4051bea28ccf660cd21f4b2ef54bbe86a186334f34"
  },
  "proxies": [
    {
      "address": "0xd58935e1753Cb4AA9906a37441724F2b3B13Cbea",
      "txHash": "0xb3f44da37051b67da866414c314a042be94b4ec1b8ea23cde7f479ec3cc4a4a3",
      "kind": "transparent"
    },
    {
      "address": "0x6cC3f9434ba34E1c94CFeC07AAaF8c72d55b074e",
      "txHash": "0xdd1bf644eb354cdd71d007af78af8586b95dc47ba949770ac5fb87f953e12234",
      "kind": "transparent"
    }
  ],
  "impls": {
    "2b862cc284752b12e95bc814afc1bfaaf793da4dc895ef72c1fcb2fe7ae0cb6d": {
      "address": "0x5C605F7754fe3D67122Bb2d42FdFDd9a6a31DF26",
      "txHash": "0xcbcd77cf528e469c33889fd85cedc04c33af82f0f699e48fd29ddcb8219f53a7",
      "layout": {
        "solcVersion": "0.8.16",
        "storage": [
          {
            "label": "_initialized",
            "offset": 0,
            "slot": "0",
            "type": "t_uint8",
            "contract": "Initializable",
            "src": "@openzeppelin\\contracts-upgradeable\\proxy\\utils\\Initializable.sol:62",
            "retypedFrom": "bool"
          },
          {
            "label": "_initializing",
            "offset": 1,
            "slot": "0",
            "type": "t_bool",
            "contract": "Initializable",
            "src": "@openzeppelin\\contracts-upgradeable\\proxy\\utils\\Initializable.sol:67"
          },
          {
            "label": "__gap",
            "offset": 0,
            "slot": "1",
            "type": "t_array(t_uint256)50_storage",
            "contract": "ContextUpgradeable",
            "src": "@openzeppelin\\contracts-upgradeable\\utils\\ContextUpgradeable.sol:36"
          },
          {
            "label": "_owner",
            "offset": 0,
            "slot": "51",
            "type": "t_address",
            "contract": "OwnableUpgradeable",
            "src": "@openzeppelin\\contracts-upgradeable\\access\\OwnableUpgradeable.sol:22"
          },
          {
            "label": "__gap",
            "offset": 0,
            "slot": "52",
            "type": "t_array(t_uint256)49_storage",
            "contract": "OwnableUpgradeable",
            "src": "@openzeppelin\\contracts-upgradeable\\access\\OwnableUpgradeable.sol:94"
          },
          {
            "label": "learnToEarn",
            "offset": 0,
            "slot": "101",
            "type": "t_address",
            "contract": "TokenFactory",
            "src": "contracts\\TokenFactory.sol:18"
          },
          {
            "label": "templateNFTReward",
            "offset": 0,
            "slot": "102",
            "type": "t_contract(INFTReward)7985",
            "contract": "TokenFactory",
            "src": "contracts\\TokenFactory.sol:24"
          }
        ],
        "types": {
          "t_address": {
            "label": "address",
            "numberOfBytes": "20"
          },
          "t_array(t_uint256)49_storage": {
            "label": "uint256[49]",
            "numberOfBytes": "1568"
          },
          "t_array(t_uint256)50_storage": {
            "label": "uint256[50]",
            "numberOfBytes": "1600"
          },
          "t_bool": {
            "label": "bool",
            "numberOfBytes": "1"
          },
          "t_contract(INFTReward)7985": {
            "label": "contract INFTReward",
            "numberOfBytes": "20"
          },
          "t_uint256": {
            "label": "uint256",
            "numberOfBytes": "32"
          },
          "t_uint8": {
            "label": "uint8",
            "numberOfBytes": "1"
          }
        }
      }
    },
    "0e57d8535ee18e47af3af77bde12e8629bcc65c2da3ade234a3675d67afaf674": {
      "address": "0x3D9aac7E9c40F86aDC8f55AEcCeBf6F22315423A",
      "txHash": "0x87c92a4fae64503ab0bb459cc543d8eff15f17bd8bc1e37092e0c86b5a2643c0",
      "layout": {
        "solcVersion": "0.8.16",
        "storage": [
          {
            "label": "_initialized",
            "offset": 0,
            "slot": "0",
            "type": "t_uint8",
            "contract": "Initializable",
            "src": "@openzeppelin\\contracts-upgradeable\\proxy\\utils\\Initializable.sol:62",
            "retypedFrom": "bool"
          },
          {
            "label": "_initializing",
            "offset": 1,
            "slot": "0",
            "type": "t_bool",
            "contract": "Initializable",
            "src": "@openzeppelin\\contracts-upgradeable\\proxy\\utils\\Initializable.sol:67"
          },
          {
            "label": "_status",
            "offset": 0,
            "slot": "1",
            "type": "t_uint256",
            "contract": "ReentrancyGuardUpgradeable",
            "src": "@openzeppelin\\contracts-upgradeable\\security\\ReentrancyGuardUpgradeable.sol:38"
          },
          {
            "label": "__gap",
            "offset": 0,
            "slot": "2",
            "type": "t_array(t_uint256)49_storage",
            "contract": "ReentrancyGuardUpgradeable",
            "src": "@openzeppelin\\contracts-upgradeable\\security\\ReentrancyGuardUpgradeable.sol:74"
          },
          {
            "label": "__gap",
            "offset": 0,
            "slot": "51",
            "type": "t_array(t_uint256)50_storage",
            "contract": "ContextUpgradeable",
            "src": "@openzeppelin\\contracts-upgradeable\\utils\\ContextUpgradeable.sol:36"
          },
          {
            "label": "_owner",
            "offset": 0,
            "slot": "101",
            "type": "t_address",
            "contract": "OwnableUpgradeable",
            "src": "@openzeppelin\\contracts-upgradeable\\access\\OwnableUpgradeable.sol:22"
          },
          {
            "label": "__gap",
            "offset": 0,
            "slot": "102",
            "type": "t_array(t_uint256)49_storage",
            "contract": "OwnableUpgradeable",
            "src": "@openzeppelin\\contracts-upgradeable\\access\\OwnableUpgradeable.sol:94"
          },
          {
            "label": "courseData",
            "offset": 0,
            "slot": "151",
            "type": "t_mapping(t_bytes32,t_struct(Course)9468_storage)",
            "contract": "LearnToEarn",
            "src": "contracts\\LearnToEarn.sol:20"
          },
          {
            "label": "learnerData",
            "offset": 0,
            "slot": "152",
            "type": "t_mapping(t_bytes32,t_mapping(t_address,t_struct(Learner)9478_storage))",
            "contract": "LearnToEarn",
            "src": "contracts\\LearnToEarn.sol:23"
          }
        ],
        "types": {
          "t_address": {
            "label": "address",
            "numberOfBytes": "20"
          },
          "t_array(t_uint256)49_storage": {
            "label": "uint256[49]",
            "numberOfBytes": "1568"
          },
          "t_array(t_uint256)50_storage": {
            "label": "uint256[50]",
            "numberOfBytes": "1600"
          },
          "t_array(t_uint256)dyn_storage": {
            "label": "uint256[]",
            "numberOfBytes": "32"
          },
          "t_bool": {
            "label": "bool",
            "numberOfBytes": "1"
          },
          "t_bytes32": {
            "label": "bytes32",
            "numberOfBytes": "32"
          },
          "t_mapping(t_address,t_struct(Learner)9478_storage)": {
            "label": "mapping(address => struct Learner)",
            "numberOfBytes": "32"
          },
          "t_mapping(t_bytes32,t_mapping(t_address,t_struct(Learner)9478_storage))": {
            "label": "mapping(bytes32 => mapping(address => struct Learner))",
            "numberOfBytes": "32"
          },
          "t_mapping(t_bytes32,t_struct(Course)9468_storage)": {
            "label": "mapping(bytes32 => struct Course)",
            "numberOfBytes": "32"
          },
          "t_struct(Course)9468_storage": {
            "label": "struct Course",
            "members": [
              {
                "label": "creator",
                "type": "t_address",
                "offset": 0,
                "slot": "0"
              },
              {
                "label": "rewardAddress",
                "type": "t_address",
                "offset": 0,
                "slot": "1"
              },
              {
                "label": "budget",
                "type": "t_uint256",
                "offset": 0,
                "slot": "2"
              },
              {
                "label": "budgetAvailable",
                "type": "t_uint256",
                "offset": 0,
                "slot": "3"
              },
              {
                "label": "bonus",
                "type": "t_uint256",
                "offset": 0,
                "slot": "4"
              },
              {
                "label": "totalLearnersClaimedBonus",
                "type": "t_uint256",
                "offset": 0,
                "slot": "5"
              },
              {
                "label": "timeCreated",
                "type": "t_uint256",
                "offset": 0,
                "slot": "6"
              },
              {
                "label": "timeEndBonus",
                "type": "t_uint256",
                "offset": 0,
                "slot": "7"
              },
              {
                "label": "isBonusToken",
                "type": "t_bool",
                "offset": 0,
                "slot": "8"
              },
              {
                "label": "canMintNFT",
                "type": "t_bool",
                "offset": 1,
                "slot": "8"
              }
            ],
            "numberOfBytes": "288"
          },
          "t_struct(Learner)9478_storage": {
            "label": "struct Learner",
            "members": [
              {
                "label": "timeStarted",
                "type": "t_uint256",
                "offset": 0,
                "slot": "0"
              },
              {
                "label": "timeCompleted",
                "type": "t_uint256",
                "offset": 0,
                "slot": "1"
              },
              {
                "label": "timeRewarded",
                "type": "t_uint256",
                "offset": 0,
                "slot": "2"
              },
              {
                "label": "nftIds",
                "type": "t_array(t_uint256)dyn_storage",
                "offset": 0,
                "slot": "3"
              }
            ],
            "numberOfBytes": "128"
          },
          "t_uint256": {
            "label": "uint256",
            "numberOfBytes": "32"
          },
          "t_uint8": {
            "label": "uint8",
            "numberOfBytes": "1"
          }
        }
      }
    }
  }
}
